cant_stop/__init__.py
cant_stop/cli.py
python_cant_stop-0.2.0.dist-info/entry_points.txt
python_cant_stop-0.2.0.dist-info/LICENSE
python_cant_stop-0.2.0.dist-info/WHEEL
python_cant_stop-0.2.0.dist-info/METADATA
python_cant_stop-0.2.0.dist-info/RECORD
