Metadata-Version: 2.1
Name: python-cant-stop
Version: 0.2.0
Summary: Calculates Can't Stop turn scores.
Home-page: https://gitlab.com/henxing/cant_stop
License: Unlicense
Keywords: cant-stop
Author: Hugh Enxing
Author-email: henxing@gmail.com
Maintainer: Hugh Enxing
Maintainer-email: henxing@gmail.com
Requires-Python: >=3.9,<4.0
Classifier: License :: Other/Proprietary License
Classifier: Programming Language :: Python :: 3
Classifier: Programming Language :: Python :: 3.10
Classifier: Programming Language :: Python :: 3.9
Project-URL: Repository, https://gitlab.com/henxing/cant_stop
